ablisk/__init__.py
ablisk/core/__init__.py
ablisk/core/lab.py
ablisk/utils/__init__.py
ablisk/utils/helpers.py
ablisk-0.2.4.dist-info/METADATA
ablisk-0.2.4.dist-info/WHEEL
ablisk-0.2.4.dist-info/top_level.txt
ablisk-0.2.4.dist-info/RECORD
