Metadata-Version: 2.4
Name: ablisk
Version: 0.2.4
Summary: A package for streamlining the design, analysis, and decision-making of A/B tests
Author-email: Domingos de Eulária <domingosdeeulariadumba@gmail.com>
License: MIT License
Project-URL: Homepage, https://github.com/domingosdeeulariadumba/ablisk
Project-URL: Changelog, https://github.com/domingosdeeulariadumba/ablisk/Changelog
Classifier: Development Status :: 3 - Alpha
Classifier: Intended Audience :: Science/Research
Classifier: Topic :: Scientific/Engineering :: Information Analysis
Classifier: Programming Language :: Python :: 3
Classifier: Programming Language :: Python :: 3.12
Classifier: Operating System :: OS Independent
Requires-Python: >=3.12.7
Requires-Dist: numpy>=1.26.4
Requires-Dist: pandas>=2.2.2
Requires-Dist: scipy>=1.15.1
Requires-Dist: plotly>=5.24.1
